paltas/__init__.py
paltas/generate.py
paltas/Analysis/__init__.py
paltas/Analysis/conv_models.py
paltas/Analysis/dataset_generation.py
paltas/Analysis/hierarchical_inference.py
paltas/Analysis/loss_functions.py
paltas/Analysis/pdf_functions.py
paltas/Analysis/posterior_functions.py
paltas/Analysis/train_model.py
paltas/Analysis/transformer_models.py
paltas/Configs/__init__.py
paltas/Configs/config_handler.py
paltas/Configs/paper_2203_00690/__init__.py
paltas/Configs/paper_2203_00690/config_test_01.py
paltas/Configs/paper_2203_00690/config_test_02.py
paltas/Configs/paper_2203_00690/config_test_03.py
paltas/Configs/paper_2203_00690/config_test_04.py
paltas/Configs/paper_2203_00690/config_test_05.py
paltas/Configs/paper_2203_00690/config_test_06.py
paltas/Configs/paper_2203_00690/config_test_07.py
paltas/Configs/paper_2203_00690/config_test_08.py
paltas/Configs/paper_2203_00690/config_test_09.py
paltas/Configs/paper_2203_00690/config_test_10.py
paltas/Configs/paper_2203_00690/config_test_11.py
paltas/Configs/paper_2203_00690/config_test_12.py
paltas/Configs/paper_2203_00690/config_test_13.py
paltas/Configs/paper_2203_00690/config_test_14.py
paltas/Configs/paper_2203_00690/config_test_15.py
paltas/Configs/paper_2203_00690/config_test_16.py
paltas/Configs/paper_2203_00690/config_test_17.py
paltas/Configs/paper_2203_00690/config_test_18.py
paltas/Configs/paper_2203_00690/config_test_19.py
paltas/Configs/paper_2203_00690/config_test_20.py
paltas/Configs/paper_2203_00690/config_test_high_m_min.py
paltas/Configs/paper_2203_00690/config_test_large_cone_angle.py
paltas/Configs/paper_2203_00690/config_test_large_los_dz.py
paltas/Configs/paper_2203_00690/config_test_low_m_min.py
paltas/Configs/paper_2203_00690/config_test_source_smoothing.py
paltas/Configs/paper_2203_00690/config_train.py
paltas/Configs/paper_2203_00690/config_val.py
paltas/MainDeflector/__init__.py
paltas/MainDeflector/main_deflector_base.py
paltas/MainDeflector/simple_deflectors.py
paltas-0.2.0.dist-info/LICENSE
paltas-0.2.0.dist-info/METADATA
paltas-0.2.0.dist-info/WHEEL
paltas-0.2.0.dist-info/top_level.txt
paltas-0.2.0.dist-info/RECORD
