Metadata-Version: 2.1
Name: paltas
Version: 0.2.0
Summary: Strong lens substructure package.
Home-page: https://github.com/swagnercarena/paltas
Author: Sebastian Wagner-Carena
Author-email: sebaswagner@outlook.com
License: MIT
License-File: LICENSE
Requires-Dist: astropy >=4.0.0
Requires-Dist: colossus
Requires-Dist: drizzle >=1.13.3
Requires-Dist: lenstronomy >=1.11.6
Requires-Dist: numpy <=1.24,>=1.13
Requires-Dist: scipy >=1.7
Requires-Dist: tqdm >=4.42.1
Requires-Dist: pandas >=1.0.1
Requires-Dist: numba >=0.52.0
Requires-Dist: matplotlib >=3.3.3
Requires-Dist: pyyaml
Requires-Dist: h5py
